CLASHChimeras-0.2.data/scripts/align-for-chimeras
CLASHChimeras-0.2.data/scripts/download-for-chimeras
CLASHChimeras-0.2.data/scripts/find-chimeras
CLASHChimeras-0.2.dist-info/DESCRIPTION.rst
CLASHChimeras-0.2.dist-info/METADATA
CLASHChimeras-0.2.dist-info/RECORD
CLASHChimeras-0.2.dist-info/WHEEL
CLASHChimeras-0.2.dist-info/metadata.json
CLASHChimeras-0.2.dist-info/top_level.txt
clashchimeras/__init__.py
clashchimeras/align.py
clashchimeras/download.py
clashchimeras/find.py
clashchimeras/initialize.py
clashchimeras/log.py
clashchimeras/methods.py
clashchimeras/parsers.py
clashchimeras/runners.py
